[
    {
      "author_name": "Manoj Kumar",
      "author_url": "https://www.google.com/maps/contrib/116971326920326126291/reviews",
      "language": "en",
      "profile_photo_url": "https://lh3.googleusercontent.com/a-/AOh14Ghe4tFlInoDofkTw5ftNmFEyHDFRFiFQYJSoqfHPA=s128-c0x00000000-cc-rp-mo-ba2",
      "rating": 5,
      "relative_time_description": "5 months ago",
      "text": "Learnt a lot about the design process. A really great course and really well explained.",
      "time": 1608200698
    },
    {
      "author_name": "Pranav Mathur",
      "author_url": "https://www.google.com/maps/contrib/117452751502769943283/reviews",
      "language": "en",
      "profile_photo_url": "https://lh3.googleusercontent.com/a-/AOh14GiBrkTeSGOvjl8tlchr3ZJZpaJjc7WMjC71CzbcQw=s128-c0x00000000-cc-rp-mo",
      "rating": 5,
      "relative_time_description": "6 months ago",
      "text": "This course really helps me to focus my product development journey. The author explains the process very clearly. Highly recommended",
      "time": 1604746277
    },
    {
      "author_name": "Arka Dey",
      "author_url": "https://www.google.com/maps/contrib/117826144716407201075/reviews",
      "language": "en",
      "profile_photo_url": "https://lh3.googleusercontent.com/a-/AOh14GixRWNL5VZozwOvpLc2XjwOt8Q3T47WKixwMf1cqA=s128-c0x00000000-cc-rp-mo",
      "rating": 5,
      "relative_time_description": "1 month ago",
      "text": "Good content and lessons. Recommended if you’re new to design sprint or need to simplify your product vision and goals.",
      "time": 1595289475
    },
    {
      "author_name": "Mahesh Vaidya",
      "author_url": "https://www.google.com/maps/contrib/114104973877747443050/reviews",
      "language": "en",
      "profile_photo_url": "https://lh3.googleusercontent.com/a/AATXAJzjfvUBiH1VeHYVGEfZnu5QLBdhu0z4AvRiv77z=s128-c0x00000000-cc-rp-mo",
      "rating": 5,
      "relative_time_description": "6 months ago",
      "text": "This course is easy to understand and breaks down the whole process to something so simple. It gives people like me the confidence to design my own app.",
      "time": 1605063010
    },
    {
      "author_name": "Nitin Sharma",
      "author_url": "https://www.google.com/maps/contrib/114791401619083218858/reviews",
      "language": "en",
      "profile_photo_url": "https://lh3.googleusercontent.com/a-/AOh14GgosVghG-pRz6KMDqlpJJ8wqEkQXudbu5Ec0vcNtw=s128-c0x00000000-cc-rp-mo-ba2",
      "rating": 5,
      "relative_time_description": "3 months ago",
      "text": "If you’re stuck on your idea for a software, web, or app, this is a good course to learn what to do next.",
      "time": 1505754200
    }
  ]
  